README.rst
setup.py
NanoSplit.egg-info/PKG-INFO
NanoSplit.egg-info/SOURCES.txt
NanoSplit.egg-info/dependency_links.txt
NanoSplit.egg-info/entry_points.txt
NanoSplit.egg-info/requires.txt
NanoSplit.egg-info/top_level.txt
nanosplit/NanoSplit.py
nanosplit/__init__.py
nanosplit/version.py